unicef_security/__init__.py
unicef_security/admin.py
unicef_security/apps.py
unicef_security/backends.py
unicef_security/config.py
unicef_security/context_processors.py
unicef_security/graph.py
unicef_security/middleware.py
unicef_security/models.py
unicef_security/pipeline.py
unicef_security/urls.py
unicef_security/utils.py
unicef_security/version.py
unicef_security/views.py
unicef_security/migrations/0001_initial.py
unicef_security/migrations/0002_auto_20201028_0154.py
unicef_security/migrations/0003_auto_20220406_2307.py
unicef_security/migrations/0004_delete_user.py
unicef_security/migrations/__init__.py
unicef_security/templates/403.html
unicef_security/templates/404.html
unicef_security/templates/500.html
unicef_security/templates/unauthorized.html
unicef_security/templates/admin/ad.html
unicef_security/templates/admin/base.html
unicef_security/templates/admin/base_site.html
unicef_security/templates/admin/link_user.html
unicef_security/templates/admin/load_users.html
unicef_security/templates/admin/login.html
unicef_security/templatetags/__init__.py
unicef_security/templatetags/security.py
unicef_security-1.9.2.dist-info/METADATA
unicef_security-1.9.2.dist-info/WHEEL
unicef_security-1.9.2.dist-info/licenses/LICENSE
unicef_security-1.9.2.dist-info/RECORD
