Metadata-Version: 2.4
Name: unicef-security
Version: 1.9.2
Summary: Provides Basic UNICEF User model and integration with Azure
Project-URL: Homepage, https://github.com/unicef/unicef-security
Author-email: UNICEF <rapidpro@unicef.org>
License-Expression: Apache-2.0 OR MIT
License-File: LICENSE
Classifier: Environment :: Web Environment
Classifier: Framework :: Django
Classifier: Framework :: Django :: 3.2
Classifier: Framework :: Django :: 4.2
Classifier: Framework :: Django :: 5.2
Classifier: Intended Audience :: Developers
Classifier: Programming Language :: Python :: 3 :: Only
Classifier: Programming Language :: Python :: 3.9
Classifier: Programming Language :: Python :: 3.10
Classifier: Programming Language :: Python :: 3.11
Classifier: Programming Language :: Python :: 3.12
Classifier: Programming Language :: Python :: 3.13
Requires-Dist: celery
Requires-Dist: cryptography
Requires-Dist: django
Requires-Dist: django-admin-extra-buttons
Requires-Dist: django-constance
Requires-Dist: django-countries
Requires-Dist: django-picklefield
Requires-Dist: pyjwt
Requires-Dist: requests
Requires-Dist: social-auth-app-django
